README.rst
setup.cfg
setup.py
silktool/__init__.py
silktool/_version.py
silktool/main.py
silktool/tool.py
silktool/util.py
silktool.egg-info/PKG-INFO
silktool.egg-info/SOURCES.txt
silktool.egg-info/dependency_links.txt
silktool.egg-info/entry_points.txt
silktool.egg-info/requires.txt
silktool.egg-info/top_level.txt
tests/__init__.py
tests/test_demoTool.py