Metadata-Version: 1.1
Name: silktool
Version: 0.0.4
Summary: Tooler app to create layout for other tools
Home-page: UNKNOWN
Author: Binay Kumar Ray
Author-email: binayray2009@gmail.com
License: UNKNOWN
Platform: UNKNOWN
Classifier: Development Status :: 4 - Beta
Classifier: Intended Audience :: Developers
Classifier: License :: Other/Proprietary License
Classifier: Natural Language :: English
Classifier: Programming Language :: Python :: 2.7
Classifier: Operating System :: OS Independent
